assistant.py
muonry/__init__.py
muonry/cli.py
muonry-0.1.5.dist-info/licenses/LICENSE
tools/__init__.py
tools/apply_patch.py
tools/build_analyzer.py
tools/deepwiki.py
tools/orchestrator.py
tools/orchestratorv2.py
tools/shell.py
tools/toolset.py
tools/update_plan.py
tools/websearch.py
muonry-0.1.5.dist-info/METADATA
muonry-0.1.5.dist-info/WHEEL
muonry-0.1.5.dist-info/entry_points.txt
muonry-0.1.5.dist-info/top_level.txt
muonry-0.1.5.dist-info/RECORD
