Metadata-Version: 2.4
Name: muonry
Version: 0.1.5
Summary: Muonry - Sequential AI coding assistant with planning, websearch, and resilient fallbacks
Author: Muonry Contributors
License: Apache License
Project-URL: Homepage, https://github.com/justrach/muonry
Project-URL: Website, https://muonry.com
Keywords: ai,assistant,coding,cli,llm
Classifier: Programming Language :: Python :: 3
Classifier: Programming Language :: Python :: 3 :: Only
Classifier: Programming Language :: Python :: 3.10
Classifier: Programming Language :: Python :: 3.11
Classifier: Programming Language :: Python :: 3.12
Classifier: Programming Language :: Python :: 3.13
Classifier: License :: OSI Approved :: Apache Software License
Classifier: Environment :: Console
Classifier: Topic :: Software Development :: Libraries
Classifier: Topic :: Software Development :: Code Generators
Requires-Python: >=3.10
License-File: LICENSE
Requires-Dist: python-dotenv>=1.0.0
Requires-Dist: orjson>=3.9.0
Provides-Extra: llm
Requires-Dist: bhumi>=0.4.1; extra == "llm"
Provides-Extra: websearch
Requires-Dist: exa_py>=1.0.0; extra == "websearch"
Dynamic: license-file
